{
	"class" : {
		"on:getState:action:label:" : "LS 6/14/2018 14:41" },
	"instance" : {
		"doClickableAction" : "LS 6/14/2018 15:16",
		"enabled" : "LS 6/19/2018 20:56",
		"enabled:" : "LS 6/19/2018 20:51",
		"getColorSelector" : "LS 6/14/2018 14:49",
		"getColorSelector:" : "LS 6/19/2018 21:19",
		"getEnabledSelector" : "LS 6/14/2018 14:49",
		"getEnabledSelector:" : "LS 6/19/2018 21:19",
		"getLabelSelector" : "LS 6/19/2018 21:09",
		"getLabelSelector:" : "LS 6/19/2018 21:10",
		"getStateSelector" : "LS 6/14/2018 14:43",
		"getStateSelector:" : "LS 6/19/2018 21:10",
		"handlesMouseDown:" : "LS 6/19/2018 20:56",
		"handlesMouseOver:" : "LS 6/19/2018 20:56",
		"handlesMouseOverDragging:" : "LS 6/19/2018 20:56",
		"model" : "LS 6/14/2018 14:43",
		"model:" : "LS 6/14/2018 14:43",
		"on:getState:action:label:" : "LS 6/14/2018 14:42",
		"style:" : "LS 6/14/2018 14:46",
		"update:" : "LS 6/19/2018 21:22",
		"updateFillStyle" : "LS 6/19/2018 21:13",
		"updateMap" : "LS 6/19/2018 21:18",
		"updateMap:" : "LS 6/19/2018 21:18",
		"whenChanged:update:" : "LS 6/14/2018 14:52" } }
